setup.py
xy_cnwords/__init__.py
xy_cnwords.egg-info/PKG-INFO
xy_cnwords.egg-info/SOURCES.txt
xy_cnwords.egg-info/dependency_links.txt
xy_cnwords.egg-info/top_level.txt
xy_cnwords/snownlp/__init__.py
xy_cnwords/snownlp/classification/__init__.py
xy_cnwords/snownlp/classification/bayes.py
xy_cnwords/snownlp/normal/__init__.py
xy_cnwords/snownlp/normal/pinyin.py
xy_cnwords/snownlp/normal/zh.py
xy_cnwords/snownlp/seg/__init__.py
xy_cnwords/snownlp/seg/seg.py
xy_cnwords/snownlp/seg/y09_2047.py
xy_cnwords/snownlp/sentiment/__init__.py
xy_cnwords/snownlp/sim/__init__.py
xy_cnwords/snownlp/sim/bm25.py
xy_cnwords/snownlp/summary/__init__.py
xy_cnwords/snownlp/summary/textrank.py
xy_cnwords/snownlp/summary/words_merge.py
xy_cnwords/snownlp/tag/__init__.py
xy_cnwords/snownlp/utils/__init__.py
xy_cnwords/snownlp/utils/frequency.py
xy_cnwords/snownlp/utils/good_turing.py
xy_cnwords/snownlp/utils/tnt.py
xy_cnwords/snownlp/utils/trie.py